SESNSLib/SESNS.py
SESNSLib/__init__.py
sesnslib-0.0.1.dist-info/METADATA
sesnslib-0.0.1.dist-info/WHEEL
sesnslib-0.0.1.dist-info/licenses/LICENSE
sesnslib-0.0.1.dist-info/RECORD
